increff_runner/__init__.py
increff_runner/function.py
increff_runner/commons/algo_block_downloader.py
increff_runner/commons/callback_helper.py
increff_runner/commons/constants.py
increff_runner/commons/db_helper.py
increff_runner/commons/db_service.py
increff_runner/commons/event_helper.py
increff_runner/commons/graphdb_helper.py
increff_runner/commons/mse_helper.py
increff_runner/commons/setup.py
increff_runner/commons/slack_util.py
increff_runner/commons/utils.py
increff_runner-12.7.dist-info/METADATA
increff_runner-12.7.dist-info/WHEEL
increff_runner-12.7.dist-info/top_level.txt
increff_runner-12.7.dist-info/RECORD
