Metadata-Version: 2.4
Name: increff_runner
Version: 12.7
Summary: Algo Runner For Increff CaaS
Author: Unnikrishnan A S
Author-email: unnikrishnan.as@increff.com
Requires-Dist: pytz==2023.3.post1
Requires-Dist: requests==2.31.0
Requires-Dist: azure-functions==1.12.0
Requires-Dist: azure-storage-blob==12.19.0
Requires-Dist: azure-storage-file-datalake==12.9.1
Requires-Dist: APScheduler==3.6.3
Requires-Dist: PyGithub==2.1.1
Requires-Dist: pymongo==4.6.1
Requires-Dist: azure-eventgrid==4.14.0
Requires-Dist: logging-increff==3.0
Requires-Dist: kubernetes==29.0.0
Requires-Dist: slack_sdk==3.29.0
Dynamic: author
Dynamic: author-email
Dynamic: description
Dynamic: description-content-type
Dynamic: requires-dist
Dynamic: summary
